limin/__init__.py
limin/agent.py
limin/py.typed
limin/structured_completion.py
limin/text_completion.py
limin/tool_call.py
limin/base/__init__.py
limin/base/base_util.py
limin/base/conversation.py
limin/base/logprobs.py
limin/base/message.py
limin/base/model_configuration.py
limin/base/structured_completion.py
limin/base/text_completion.py
limin/base/tool.py
limin-0.9.1.dist-info/METADATA
limin-0.9.1.dist-info/WHEEL
limin-0.9.1.dist-info/top_level.txt
limin-0.9.1.dist-info/RECORD
