Metadata-Version: 2.4
Name: limin
Version: 0.9.1
Summary: A Python library for interacting with OpenAI-compatible LLM APIs.
Author-email: Titanom Solutions <infrastructure@titanom.com>
Requires-Python: >=3.10
Requires-Dist: openai==1.69.0
Requires-Dist: tqdm==4.67.1
